LICENSE
MANIFEST.in
README.md
requirements.txt
setup.py
tox.ini
django_mongo_connection.egg-info/PKG-INFO
django_mongo_connection.egg-info/SOURCES.txt
django_mongo_connection.egg-info/dependency_links.txt
django_mongo_connection.egg-info/not-zip-safe
django_mongo_connection.egg-info/requires.txt
django_mongo_connection.egg-info/top_level.txt
mongo_connection/__init__.py
mongo_connection/apps.py
mongo_connection/constants.py
mongo_connection/loading.py
tests/__init__.py
tests/run_tests.py
tests/settings.py
tests/test_constants.py
tests/test_loading.py
tests/urls.py
tests/wsgi.py